structuredxtract/__init__.py
structuredxtract/main.py
structuredxtract/prompts.py
structuredxtract-2025.12.21145156.dist-info/METADATA
structuredxtract-2025.12.21145156.dist-info/WHEEL
structuredxtract-2025.12.21145156.dist-info/top_level.txt
structuredxtract-2025.12.21145156.dist-info/RECORD
