Metadata-Version: 2.4
Name: structuredxtract
Version: 2025.12.21145156
Summary: A new package is designed to simplify the process of extracting structured information from user-provided text inputs by leveraging a language model with pattern matching capabilities. The system prom
Author-email: structuredxtract <hi@eugene.plus>
License: MIT
Project-URL: Homepage, https://github.com/chigwell/structuredxtract
Requires-Python: >=3.9
Requires-Dist: langchain-llm7>=0.0.0
Requires-Dist: llmatch-messages>=0.0.0
Requires-Dist: langchain-core>=0.3.0
